insecure_mcp_server/__init__.py
insecure_mcp_server/server.py
mcp_scanner/__init__.py
mcp_scanner/auth.py
mcp_scanner/cli.py
mcp_scanner/http_checks.py
mcp_scanner/models.py
mcp_scanner/scanner.py
mcp_scanner/scanner_specs.schema
mcp_scanner/spec.py
mcp_scanner/sse_scanner.py
mcp_scanner/stdio_scanner.py
mcp_security_scanner-0.1.3.dist-info/licenses/LICENSE
mcp_security_scanner-0.1.3.dist-info/METADATA
mcp_security_scanner-0.1.3.dist-info/WHEEL
mcp_security_scanner-0.1.3.dist-info/entry_points.txt
mcp_security_scanner-0.1.3.dist-info/top_level.txt
mcp_security_scanner-0.1.3.dist-info/RECORD
