Metadata-Version: 2.4
Name: mcp-security-scanner
Version: 0.1.3
Summary: Security scanner for Model Context Protocol (MCP) servers
Author-email: MCP Scanner <huzaifas@redhat.com>
License:                                  Apache License
License-File: LICENSE
Requires-Dist: click>=8.1
Requires-Dist: websockets>=12.0
Requires-Dist: httpx>=0.27
Requires-Dist: httpx-sse>=0.4
Requires-Dist: jsonschema>=4.21
Requires-Dist: pydantic>=2.6
Requires-Dist: rich>=13.7
Requires-Dist: pytest>=8.3
Dynamic: license-file
